sentence_cut/__init__.py
sentence_cut/sentence_cut.py
sentence_cut-0.0.2.dist-info/LICENSE
sentence_cut-0.0.2.dist-info/METADATA
sentence_cut-0.0.2.dist-info/WHEEL
sentence_cut-0.0.2.dist-info/top_level.txt
sentence_cut-0.0.2.dist-info/RECORD
