Metadata-Version: 2.1
Name: sentence-cut
Version: 0.0.2
Summary: sentence cut.
Home-page: UNKNOWN
Author: Yu
Author-email: t-yhan@microsoft.com
License: UNKNOWN
Platform: UNKNOWN
Classifier: Programming Language :: Python :: 3
Classifier: License :: OSI Approved :: MIT License
Classifier: Operating System :: OS Independent
Requires-Python: >=3.6
